appctx/__init__.py
appctx/container.py
appctx/decorators.py
appctx/py.typed
appctx-0.1.0.dist-info/METADATA
appctx-0.1.0.dist-info/WHEEL
appctx-0.1.0.dist-info/top_level.txt
appctx-0.1.0.dist-info/RECORD
