Metadata-Version: 2.4
Name: appctx
Version: 0.1.0
Summary: Spring style dependency injection for python
Author-email: wssccc <wssccc@qq.com>
License: MIT
Project-URL: Homepage, https://github.com/wssccc/appctx
Project-URL: Repository, https://github.com/wssccc/appctx
Project-URL: Bug Tracker, https://github.com/wssccc/appctx/issues
Project-URL: Documentation, https://github.com/wssccc/appctx#readme
Classifier: Development Status :: 3 - Alpha
Classifier: Intended Audience :: Developers
Classifier: Programming Language :: Python :: 3
Classifier: Programming Language :: Python :: 3.8
Classifier: Programming Language :: Python :: 3.9
Classifier: Programming Language :: Python :: 3.10
Classifier: Programming Language :: Python :: 3.11
Classifier: Topic :: Software Development :: Libraries :: Python Modules
Requires-Python: >=3.8
Provides-Extra: dev
Requires-Dist: pytest>=7.0; extra == "dev"
Requires-Dist: pytest-cov>=4.0; extra == "dev"
Requires-Dist: black>=22.0; extra == "dev"
Requires-Dist: flake8>=5.0; extra == "dev"
Requires-Dist: mypy>=1.0; extra == "dev"
Requires-Dist: isort>=5.0; extra == "dev"
